yaeos/__init__.py
yaeos/constants.py
yaeos/core.py
yaeos/envelopes.py
yaeos/gpec.py
yaeos/fitting/__init__.py
yaeos/fitting/core.py
yaeos/fitting/model_setters.py
yaeos/fitting/solvers.py
yaeos/lib/__init__.py
yaeos/lib/yaeos_python.cpython-312-x86_64-linux-gnu.so
yaeos/models/__init__.py
yaeos/models/groups.py
yaeos/models/excess_gibbs/__init__.py
yaeos/models/excess_gibbs/dortmund.py
yaeos/models/excess_gibbs/nrtl.py
yaeos/models/excess_gibbs/psrk_unifac.py
yaeos/models/excess_gibbs/unifac.py
yaeos/models/excess_gibbs/uniquac.py
yaeos/models/residual_helmholtz/__init__.py
yaeos/models/residual_helmholtz/cubic_eos/__init__.py
yaeos/models/residual_helmholtz/cubic_eos/cubic_eos.py
yaeos/models/residual_helmholtz/cubic_eos/mixing_rules.py
yaeos/models/residual_helmholtz/multifluid/__init__.py
yaeos/models/residual_helmholtz/multifluid/gerg2008.py
yaeos/models/residual_helmholtz/saft/__init__.py
yaeos/models/residual_helmholtz/saft/pcsaft.py
yaeos.libs/libblas-fe34f726.so.3.8.0
yaeos.libs/libgfortran-83c28eba.so.5.0.0
yaeos.libs/libgomp-e985bcbb.so.1.0.0
yaeos.libs/liblapack-31d7d384.so.3.8.0
yaeos.libs/libquadmath-2284e583.so.0.0.0
yaeos-4.4.0.dist-info/METADATA
yaeos-4.4.0.dist-info/WHEEL
yaeos-4.4.0.dist-info/RECORD
yaeos-4.4.0.dist-info/sboms/auditwheel.cdx.json
