Metadata-Version: 2.1
Name: yaeos
Version: 4.4.0
Summary: Thermodynamic modelling with Equations of State
Requires-Python: >=3.10
Requires-Dist: IPython
Requires-Dist: numpy
Requires-Dist: scipy
Requires-Dist: pandas
Requires-Dist: intersect
Requires-Dist: matplotlib
